{
  "parent": "minecraftmythologicalmod:pyxis_item",
  "criteria": {
    "has_Iris_Pyxis": {
      "conditions": {
        "items": [
          {
            "items": [
              "minecraftmythologicalmod:iris_pyxis"
            ]
          }
        ]
      },
      "trigger": "minecraft:inventory_changed"
    }
  },
  "display": {
    "announce_to_chat": true,
    "description": {
      "text": "\ncraft an iris pyxis out of pyxis and iris. Amazing!!!"
    },
    "frame": "task",
    "hidden": false,
    "icon": {
      "item": "minecraftmythologicalmod:iris_pyxis"
    },
    "show_toast": true,
    "title": {
      "text": "Iris_Pyxis"
    }
  },
  "requirements": [
    [
      "has_Iris_Pyxis"
    ]
  ],
  "sends_telemetry_event": true
}